[
  {
    "inputs": [
      { "internalType": "address", "name": "user", "type": "address" },
      { "internalType": "uint256", "name": "dueDate", "type": "uint256" }
    ],
    "name": "CoolingOffPeriod",
    "type": "error"
  },
  {
    "inputs": [
      { "internalType": "uint256", "name": "current", "type": "uint256" },
      { "internalType": "uint256", "name": "deadline", "type": "uint256" }
    ],
    "name": "ExpiredSignature",
    "type": "error"
  },
  {
    "inputs": [
      { "internalType": "uint256", "name": "target", "type": "uint256" },
      { "internalType": "uint256", "name": "actual", "type": "uint256" }
    ],
    "name": "InsufficientALPOutput",
    "type": "error"
  },
  {
    "inputs": [
      { "internalType": "int256", "name": "amountUsd", "type": "int256" }
    ],
    "name": "InsufficientLiquidityPool",
    "type": "error"
  },
  {
    "inputs": [
      { "internalType": "address", "name": "token", "type": "address" },
      { "internalType": "uint256", "name": "target", "type": "uint256" },
      { "internalType": "uint256", "name": "actual", "type": "uint256" }
    ],
    "name": "InsufficientTokenOutput",
    "type": "error"
  },
  { "inputs": [], "name": "InvalidAmount", "type": "error" },
  { "inputs": [], "name": "InvalidSignature", "type": "error" },
  {
    "inputs": [
      {
        "internalType": "uint256",
        "name": "currentChainId",
        "type": "uint256"
      },
      {
        "internalType": "uint256",
        "name": "unsupportedChainId",
        "type": "uint256"
      }
    ],
    "name": "UnsupportedChain",
    "type": "error"
  },
  {
    "inputs": [
      { "internalType": "address", "name": "token", "type": "address" }
    ],
    "name": "UnsupportedToken",
    "type": "error"
  },
  { "inputs": [], "name": "ZeroAddress", "type": "error" },
  {
    "anonymous": false,
    "inputs": [
      {
        "indexed": true,
        "internalType": "address",
        "name": "account",
        "type": "address"
      },
      {
        "indexed": true,
        "internalType": "address",
        "name": "receiver",
        "type": "address"
      },
      {
        "indexed": true,
        "internalType": "address",
        "name": "tokenOut",
        "type": "address"
      },
      {
        "indexed": false,
        "internalType": "uint256",
        "name": "alpAmount",
        "type": "uint256"
      },
      {
        "indexed": false,
        "internalType": "uint256",
        "name": "amountOut",
        "type": "uint256"
      }
    ],
    "name": "BurnAlp",
    "type": "event"
  },
  {
    "anonymous": false,
    "inputs": [
      {
        "indexed": true,
        "internalType": "address",
        "name": "account",
        "type": "address"
      },
      {
        "indexed": true,
        "internalType": "address",
        "name": "tokenOut",
        "type": "address"
      },
      {
        "indexed": false,
        "internalType": "uint256",
        "name": "amountOut",
        "type": "uint256"
      },
      {
        "indexed": false,
        "internalType": "uint256",
        "name": "tokenOutPrice",
        "type": "uint256"
      },
      {
        "indexed": false,
        "internalType": "uint256",
        "name": "burnFeeUsd",
        "type": "uint256"
      },
      {
        "indexed": false,
        "internalType": "uint256",
        "name": "alpAmount",
        "type": "uint256"
      }
    ],
    "name": "BurnFee",
    "type": "event"
  },
  {
    "anonymous": false,
    "inputs": [
      {
        "indexed": true,
        "internalType": "address",
        "name": "account",
        "type": "address"
      },
      {
        "indexed": true,
        "internalType": "address",
        "name": "token",
        "type": "address"
      },
      {
        "indexed": false,
        "internalType": "uint256",
        "name": "amount",
        "type": "uint256"
      }
    ],
    "name": "BurnRemoveLiquidity",
    "type": "event"
  },
  {
    "anonymous": false,
    "inputs": [
      {
        "indexed": true,
        "internalType": "address",
        "name": "account",
        "type": "address"
      },
      {
        "indexed": true,
        "internalType": "address",
        "name": "token",
        "type": "address"
      },
      {
        "indexed": false,
        "internalType": "uint256",
        "name": "amount",
        "type": "uint256"
      }
    ],
    "name": "MintAddLiquidity",
    "type": "event"
  },
  {
    "anonymous": false,
    "inputs": [
      {
        "indexed": true,
        "internalType": "address",
        "name": "account",
        "type": "address"
      },
      {
        "indexed": true,
        "internalType": "address",
        "name": "tokenIn",
        "type": "address"
      },
      {
        "indexed": false,
        "internalType": "uint256",
        "name": "amountIn",
        "type": "uint256"
      },
      {
        "indexed": false,
        "internalType": "uint256",
        "name": "alpOut",
        "type": "uint256"
      }
    ],
    "name": "MintAlp",
    "type": "event"
  },
  {
    "anonymous": false,
    "inputs": [
      {
        "indexed": true,
        "internalType": "address",
        "name": "account",
        "type": "address"
      },
      {
        "indexed": true,
        "internalType": "address",
        "name": "tokenIn",
        "type": "address"
      },
      {
        "indexed": false,
        "internalType": "uint256",
        "name": "amountIn",
        "type": "uint256"
      },
      {
        "indexed": false,
        "internalType": "uint256",
        "name": "tokenInPrice",
        "type": "uint256"
      },
      {
        "indexed": false,
        "internalType": "uint256",
        "name": "mintFeeUsd",
        "type": "uint256"
      },
      {
        "indexed": false,
        "internalType": "uint256",
        "name": "alpAmount",
        "type": "uint256"
      }
    ],
    "name": "MintFee",
    "type": "event"
  },
  {
    "anonymous": false,
    "inputs": [
      {
        "indexed": false,
        "internalType": "address",
        "name": "account",
        "type": "address"
      }
    ],
    "name": "Paused",
    "type": "event"
  },
  {
    "anonymous": false,
    "inputs": [
      {
        "indexed": true,
        "internalType": "address",
        "name": "account",
        "type": "address"
      },
      {
        "indexed": false,
        "internalType": "bool",
        "name": "supported",
        "type": "bool"
      }
    ],
    "name": "SupportedFreeBurn",
    "type": "event"
  },
  {
    "anonymous": false,
    "inputs": [
      {
        "indexed": false,
        "internalType": "address",
        "name": "account",
        "type": "address"
      }
    ],
    "name": "Unpaused",
    "type": "event"
  },
  {
    "inputs": [],
    "name": "ALP",
    "outputs": [{ "internalType": "address", "name": "", "type": "address" }],
    "stateMutability": "view",
    "type": "function"
  },
  {
    "inputs": [
      { "internalType": "address", "name": "account", "type": "address" }
    ],
    "name": "addFreeBurnWhitelist",
    "outputs": [],
    "stateMutability": "nonpayable",
    "type": "function"
  },
  {
    "inputs": [],
    "name": "alpPrice",
    "outputs": [{ "internalType": "uint256", "name": "", "type": "uint256" }],
    "stateMutability": "view",
    "type": "function"
  },
  {
    "inputs": [
      { "internalType": "address", "name": "tokenOut", "type": "address" },
      { "internalType": "uint256", "name": "alpAmount", "type": "uint256" },
      { "internalType": "uint256", "name": "minOut", "type": "uint256" },
      { "internalType": "address", "name": "receiver", "type": "address" }
    ],
    "name": "burnAlp",
    "outputs": [],
    "stateMutability": "nonpayable",
    "type": "function"
  },
  {
    "inputs": [
      { "internalType": "uint256", "name": "alpAmount", "type": "uint256" },
      { "internalType": "uint256", "name": "minOut", "type": "uint256" },
      {
        "internalType": "address payable",
        "name": "receiver",
        "type": "address"
      }
    ],
    "name": "burnAlpBNB",
    "outputs": [],
    "stateMutability": "nonpayable",
    "type": "function"
  },
  {
    "inputs": [
      { "internalType": "uint256", "name": "alpAmount", "type": "uint256" },
      { "internalType": "uint256", "name": "minOut", "type": "uint256" },
      { "internalType": "address", "name": "receiver", "type": "address" },
      { "internalType": "bytes", "name": "message", "type": "bytes" },
      { "internalType": "bytes", "name": "signature", "type": "bytes" }
    ],
    "name": "burnAlpWithSignature",
    "outputs": [],
    "stateMutability": "nonpayable",
    "type": "function"
  },
  {
    "inputs": [],
    "name": "coolingDuration",
    "outputs": [{ "internalType": "uint256", "name": "", "type": "uint256" }],
    "stateMutability": "view",
    "type": "function"
  },
  {
    "inputs": [],
    "name": "getSigner",
    "outputs": [{ "internalType": "address", "name": "", "type": "address" }],
    "stateMutability": "view",
    "type": "function"
  },
  {
    "inputs": [
      { "internalType": "address", "name": "alpToken", "type": "address" },
      { "internalType": "address", "name": "signer", "type": "address" }
    ],
    "name": "initAlpManagerFacet",
    "outputs": [],
    "stateMutability": "nonpayable",
    "type": "function"
  },
  {
    "inputs": [
      { "internalType": "address", "name": "account", "type": "address" }
    ],
    "name": "isFreeBurn",
    "outputs": [{ "internalType": "bool", "name": "", "type": "bool" }],
    "stateMutability": "view",
    "type": "function"
  },
  {
    "inputs": [
      { "internalType": "address", "name": "account", "type": "address" }
    ],
    "name": "lastMintedTimestamp",
    "outputs": [{ "internalType": "uint256", "name": "", "type": "uint256" }],
    "stateMutability": "view",
    "type": "function"
  },
  {
    "inputs": [
      { "internalType": "address", "name": "tokenIn", "type": "address" },
      { "internalType": "uint256", "name": "amountIn", "type": "uint256" },
      { "internalType": "uint256", "name": "minAlp", "type": "uint256" },
      { "internalType": "bool", "name": "stake", "type": "bool" }
    ],
    "name": "mintAlp",
    "outputs": [],
    "stateMutability": "nonpayable",
    "type": "function"
  },
  {
    "inputs": [
      { "internalType": "uint256", "name": "minAlp", "type": "uint256" },
      { "internalType": "bool", "name": "stake", "type": "bool" }
    ],
    "name": "mintAlpBNB",
    "outputs": [],
    "stateMutability": "payable",
    "type": "function"
  },
  {
    "inputs": [
      { "internalType": "uint256", "name": "amountIn", "type": "uint256" },
      { "internalType": "uint256", "name": "minAlp", "type": "uint256" },
      { "internalType": "bool", "name": "stake", "type": "bool" },
      { "internalType": "bytes", "name": "message", "type": "bytes" },
      { "internalType": "bytes", "name": "signature", "type": "bytes" }
    ],
    "name": "mintAlpWithSignature",
    "outputs": [],
    "stateMutability": "payable",
    "type": "function"
  },
  {
    "inputs": [
      { "internalType": "address", "name": "account", "type": "address" }
    ],
    "name": "removeFreeBurnWhitelist",
    "outputs": [],
    "stateMutability": "nonpayable",
    "type": "function"
  },
  {
    "inputs": [
      {
        "internalType": "uint256",
        "name": "coolingDuration_",
        "type": "uint256"
      }
    ],
    "name": "setCoolingDuration",
    "outputs": [],
    "stateMutability": "nonpayable",
    "type": "function"
  },
  {
    "inputs": [
      { "internalType": "address", "name": "signer", "type": "address" }
    ],
    "name": "setSigner",
    "outputs": [],
    "stateMutability": "nonpayable",
    "type": "function"
  }
]
